based_latex/__init__.py
based_latex/formula.py
based_latex-0.0.61.dist-info/LICENSE.txt
based_latex-0.0.61.dist-info/METADATA
based_latex-0.0.61.dist-info/WHEEL
based_latex-0.0.61.dist-info/top_level.txt
based_latex-0.0.61.dist-info/RECORD
