Metadata-Version: 2.1
Name: based-latex
Version: 0.0.61
Summary: Generates properly baselined images and HTML code from LaTeX formulas.
Home-page: https://github.com/wircho/based_latex
Author: Adolfo Rodriguez
Author-email: adolfo@interoper.io
License: UNKNOWN
Platform: UNKNOWN
Classifier: Programming Language :: Python :: 3
Classifier: License :: OSI Approved :: MIT License
Classifier: Operating System :: OS Independent
Requires-Python: >=3.6
